stactools/fws_nwi/__init__.py
stactools/fws_nwi/commands.py
stactools/fws_nwi/constants.py
stactools/fws_nwi/geoparquet.py
stactools/fws_nwi/metadata.py
stactools/fws_nwi/stac.py
stactools/fws_nwi/states.py
stactools_fws_nwi-0.2.0.dist-info/LICENSE
stactools_fws_nwi-0.2.0.dist-info/METADATA
stactools_fws_nwi-0.2.0.dist-info/WHEEL
stactools_fws_nwi-0.2.0.dist-info/top_level.txt
stactools_fws_nwi-0.2.0.dist-info/RECORD
