Metadata-Version: 2.1
Name: stactools-fws-nwi
Version: 0.2.0
Summary: stactools package for the National Wetlands Inventory (NWI) product provided by the U.S. Fish and Wildlife Service (FWS)
Home-page: https://github.com/stactools-packages/fws-nwi
Author: Matthias Mohr, Pete Gadomski
Author-email: matthias.mohr@radiant.earth, pete.gadomski@gmail.com
Project-URL: Issues, https://github.com/stactools-packages/fws-nwi/issues
Keywords: stactools,FWS,NWI,wetland,deepwater,habitats,STAC
Classifier: Development Status :: 4 - Beta
Classifier: License :: OSI Approved :: Apache Software License
Classifier: Programming Language :: Python :: 3.8
Classifier: Programming Language :: Python :: 3.9
Classifier: Programming Language :: Python :: 3.10
License-File: LICENSE
Requires-Dist: fiona (>=1.8)
Requires-Dist: geopandas (>=0.12)
Requires-Dist: pyarrow (>=9.0)
Requires-Dist: pyproj (>=3.4)
Requires-Dist: pystac (>=1.6)
Requires-Dist: python-dateutil (>=2.8)
Requires-Dist: shapely (>=1.8)
Requires-Dist: stac-table (>=1.0.0)
Requires-Dist: stactools (>=0.4.2)
Requires-Dist: tqdm (>=4.64)
